flask_qrcode/__init__.py
tests/__init__.py
tests/server.py
tests/test_functional.py
Flask_QRcode-3.1.0.dist-info/COPYING
Flask_QRcode-3.1.0.dist-info/METADATA
Flask_QRcode-3.1.0.dist-info/WHEEL
Flask_QRcode-3.1.0.dist-info/top_level.txt
Flask_QRcode-3.1.0.dist-info/RECORD
